<?xml version="1.0" encoding="UTF-8"?>
<DiagnosticReport xmlns="http://hl7.org/fhir">
  <id value="dr-300"/>
  <text>
    <status value="generated"/>
    <div xmlns="http://www.w3.org/1999/xhtml">
      <p>
        <b>Generated Narrative with Details</b>
      </p>
      <p>
        <b>id</b>: dr-300</p>
      <p>
        <b>identifier</b>: , Placer Identifier = do-300</p>
      <p>
        <b>status</b>: final</p>
      <p>
        <b>code</b>: CBC_diff 
        <span style="background: LightGoldenRodYellow ">(Details : {http://lis.acmelabs.org/codes code "300" := "300", given as "CBC_diff"}; {LOINC code "57021-8" := "57021-8", given as "CBC W Auto Differential panel in Blood"})</span>
      </p>
      <p>
        <b>subject</b>: 
        <a href="Patient/patient-uslab-example1">Todd G. Lerr</a>
      </p>
      <p>
        <b>effective</b>: 9/25/2015</p>
      <p>
        <b>issued</b>: 9/26/2015</p>
      <p>
        <b>performer</b>: 
        <a href="Organization/org-uslab-example3">Acme Labs</a>
      </p>
      <p>
        <b>request</b>: 
        <a href="DiagnosticOrder/do-300">DiagnosticOrder/do-300</a>
      </p>
      <p>
        <b>specimen</b>: 
        <a href="Specimen/spec-uslab-example1">Blood Sample</a>
      </p>
      <p>
        <b>result</b>: </p>
      <ul>
        <li>
          <a href="Observation/obs-300">Observation/obs-300</a>
        </li>
        <li>
          <a href="Observation/obs-301">Observation/obs-301</a>
        </li>
        <li>
          <a href="Observation/obs-302">Observation/obs-302</a>
        </li>
        <li>
          <a href="Observation/obs-303">Observation/obs-303</a>
        </li>
        <li>
          <a href="Observation/obs-304">Observation/obs-304</a>
        </li>
      </ul>
    </div>
  </text>
  <identifier>
    <type>
      <coding>
        <system value="http://hl7.org/fhir/identifier-type"/>
        <code value="FILL"/>
      </coding>
    </type>
    <system value="http://lis.acmelabs.org/identifiers"/>
    <value value="dr-300"/>
  </identifier>
  <identifier>
    <type>
      <coding>
        <system value="http://hl7.org/fhir/identifier-type"/>
        <code value="PLAC"/>
      </coding>
    </type>
    <system value="http://goodhealth.org/identifiers"/>
    <value value="do-300"/>
  </identifier>
  <status value="final"/>
  <code>
    <coding>
      <system value="http://lis.acmelabs.org/codes"/>
      <code value="300"/>
      <display value="CBC_diff"/>
    </coding>
    <coding>
      <system value="http://loinc.org"/>
      <code value="57021-8"/>
      <display value="CBC W Auto Differential panel in Blood"/>
    </coding>
  </code>
  <subject>
    <reference value="Patient/patient-uslab-example1"/>
    <display value="Todd G. Lerr"/>
  </subject>
  <effectiveDateTime value="2015-09-25"/>
  <issued value="2015-09-26T00:00:00Z"/>
  <performer>
    <reference value="Organization/org-uslab-example3"/>
    <display value="Acme Labs"/>
  </performer>
  <request>
    <reference value="DiagnosticOrder/do-300"/>
    <display value="DiagnosticOrder/do-300"/>
  </request>
  <specimen>
    <reference value="Specimen/spec-uslab-example1"/>
    <display value="Blood Sample"/>
  </specimen>
  <result>
    <reference value="Observation/obs-300"/>
    <display value="Observation/obs-300"/>
  </result>
  <result>
    <reference value="Observation/obs-301"/>
    <display value="Observation/obs-301"/>
  </result>
  <result>
    <reference value="Observation/obs-302"/>
    <display value="Observation/obs-302"/>
  </result>
  <result>
    <reference value="Observation/obs-303"/>
    <display value="Observation/obs-303"/>
  </result>
  <result>
    <reference value="Observation/obs-304"/>
    <display value="Observation/obs-304"/>
  </result>
</DiagnosticReport>